{
  "$defs": {
    "AdverseDrugEvent": {
      "enum": [
        "Allergy or adverse drug event",
        "None of the above (e.g. not mentioned, patient does not have an allergy or adverse drug event related to this medication, etc)"
      ],
      "title": "AdverseDrugEvent",
      "type": "string"
    },
    "AdverseDrugEventAntiTNFMention": {
      "properties": {
        "has_mention": {
          "description": "Indicates whether the concept was mentioned in the text (false by default).",
          "title": "Has Mention",
          "type": "boolean"
        },
        "spans": {
          "description": "The verbatim text where this concept was mentioned.",
          "items": {
            "type": "string"
          },
          "title": "Spans",
          "type": "array"
        },
        "ade": {
          "$ref": "#/$defs/AdverseDrugEvent",
          "default": "None of the above (e.g. not mentioned, patient does not have an allergy or adverse drug event related to this medication, etc)",
          "description": "Did the patient have an allergy or adverse drug event related to Anti-TNF medication?"
        }
      },
      "required": [
        "has_mention",
        "spans"
      ],
      "title": "AdverseDrugEventAntiTNFMention",
      "type": "object"
    },
    "AdverseDrugEventIBDMention": {
      "properties": {
        "has_mention": {
          "description": "Indicates whether the concept was mentioned in the text (false by default).",
          "title": "Has Mention",
          "type": "boolean"
        },
        "spans": {
          "description": "The verbatim text where this concept was mentioned.",
          "items": {
            "type": "string"
          },
          "title": "Spans",
          "type": "array"
        },
        "ade": {
          "$ref": "#/$defs/AdverseDrugEvent",
          "default": "None of the above (e.g. not mentioned, patient does not have an allergy or adverse drug event related to this medication, etc)",
          "description": "Did the patient have an allergy or adverse drug event related to IBD medication?"
        }
      },
      "required": [
        "has_mention",
        "spans"
      ],
      "title": "AdverseDrugEventIBDMention",
      "type": "object"
    },
    "AntiTNFResponse": {
      "enum": [
        "Anti-TNF therapy was discontinued, therapy was escalated (eg, addition of second biologic), or surgery (eg, colectomy, ileocecectomy).",
        "Anti-TNF therapy was successful, patient shows clinical improvement or symptom reduction",
        "None of the above (e.g. not mentioned, patient was not given anti-TNF therapy, etc)"
      ],
      "title": "AntiTNFResponse",
      "type": "string"
    },
    "AntiTNFResponseMention": {
      "properties": {
        "has_mention": {
          "description": "Indicates whether the concept was mentioned in the text (false by default).",
          "title": "Has Mention",
          "type": "boolean"
        },
        "spans": {
          "description": "The verbatim text where this concept was mentioned.",
          "items": {
            "type": "string"
          },
          "title": "Spans",
          "type": "array"
        },
        "anti_tnf_response": {
          "$ref": "#/$defs/AntiTNFResponse",
          "default": "None of the above (e.g. not mentioned, patient was not given anti-TNF therapy, etc)",
          "description": "What was the anti-TNF medication response?"
        }
      },
      "required": [
        "has_mention",
        "spans"
      ],
      "title": "AntiTNFResponseMention",
      "type": "object"
    },
    "RxAnnotation": {
      "description": "A collection of medication-related mentions for a single medication instance.\nIncludes mentions of medication class, status, treatment phase, and response.",
      "properties": {
        "rx_name": {
          "anyOf": [
            {
              "type": "string"
            },
            {
              "type": "null"
            }
          ],
          "default": null,
          "description": "The name of the medication mentioned in the chart. This should be a string, and can include generic or brand names, as well as abbreviations. If multiple medications are mentioned in the same context, create separate RxAnnotation instances for each medication with their respective details.",
          "title": "Rx Name"
        },
        "rx_class_mention": {
          "$ref": "#/$defs/RxClassMention"
        },
        "rx_status_mention": {
          "$ref": "#/$defs/RxStatusMention"
        },
        "rx_treatment_phase_mention": {
          "$ref": "#/$defs/RxTreatmentPhaseMention"
        },
        "rx_response_mention": {
          "$ref": "#/$defs/RxResponseMention"
        }
      },
      "required": [
        "rx_class_mention",
        "rx_status_mention",
        "rx_treatment_phase_mention",
        "rx_response_mention"
      ],
      "title": "RxAnnotation",
      "type": "object"
    },
    "RxClass": {
      "description": "IBD Medication Class",
      "enum": [
        "Anti-TNF",
        "Anti-Interleukin",
        "Anti-Integrin",
        "Aminosalicylate",
        "Corticosteroid",
        "Immunomodulator",
        "None of the above (e.g. not mentioned, non-ibd medication, etc)"
      ],
      "title": "RxClass",
      "type": "string"
    },
    "RxClassMention": {
      "properties": {
        "has_mention": {
          "description": "Indicates whether the concept was mentioned in the text (false by default).",
          "title": "Has Mention",
          "type": "boolean"
        },
        "spans": {
          "description": "The verbatim text where this concept was mentioned.",
          "items": {
            "type": "string"
          },
          "title": "Spans",
          "type": "array"
        },
        "rx_class": {
          "$ref": "#/$defs/RxClass",
          "default": "None of the above (e.g. not mentioned, non-ibd medication, etc)",
          "description": "Which, if any, of these IBD medication classes is the patient taking currently?"
        }
      },
      "required": [
        "has_mention",
        "spans"
      ],
      "title": "RxClassMention",
      "type": "object"
    },
    "RxEffectiveness": {
      "enum": [
        "Medication was effective in treating IBD",
        "Medication failed to treat IBD",
        "None of the above (e.g. not mentioned, patient was not given IBD medication, etc)"
      ],
      "title": "RxEffectiveness",
      "type": "string"
    },
    "RxEffectivenessMention": {
      "properties": {
        "has_mention": {
          "description": "Indicates whether the concept was mentioned in the text (false by default).",
          "title": "Has Mention",
          "type": "boolean"
        },
        "spans": {
          "description": "The verbatim text where this concept was mentioned.",
          "items": {
            "type": "string"
          },
          "title": "Spans",
          "type": "array"
        },
        "rx_effectiveness": {
          "$ref": "#/$defs/RxEffectiveness",
          "default": "None of the above (e.g. not mentioned, patient was not given IBD medication, etc)",
          "description": "Are the patient medications effective in treating IBD?"
        }
      },
      "required": [
        "has_mention",
        "spans"
      ],
      "title": "RxEffectivenessMention",
      "type": "object"
    },
    "RxResponse": {
      "enum": [
        "COMPLETE_RESPONSE",
        "PARTIAL_RESPONSE",
        "MINOR_RESPONSE",
        "STABLE_DISEASE",
        "PROGRESSIVE_DISEASE",
        "MIXED_RESPONSE",
        "PSEUDOPROGRESSION",
        "NOT_EVALUABLE",
        "None of the above (e.g. response not mentioned, something other than what is listed, etc)"
      ],
      "title": "RxResponse",
      "type": "string"
    },
    "RxResponseMention": {
      "properties": {
        "has_mention": {
          "description": "Indicates whether the concept was mentioned in the text (false by default).",
          "title": "Has Mention",
          "type": "boolean"
        },
        "spans": {
          "description": "The verbatim text where this concept was mentioned.",
          "items": {
            "type": "string"
          },
          "title": "Spans",
          "type": "array"
        },
        "rx_response": {
          "$ref": "#/$defs/RxResponse",
          "default": "None of the above (e.g. response not mentioned, something other than what is listed, etc)",
          "description": "What, if known, is the patient's response to this medication?"
        }
      },
      "required": [
        "has_mention",
        "spans"
      ],
      "title": "RxResponseMention",
      "type": "object"
    },
    "RxStartDateMention": {
      "properties": {
        "has_mention": {
          "description": "Indicates whether the concept was mentioned in the text (false by default).",
          "title": "Has Mention",
          "type": "boolean"
        },
        "spans": {
          "description": "The verbatim text where this concept was mentioned.",
          "items": {
            "type": "string"
          },
          "title": "Spans",
          "type": "array"
        },
        "ibd_medication_start_date": {
          "anyOf": [
            {
              "type": "string"
            },
            {
              "type": "null"
            }
          ],
          "default": null,
          "description": "What was the date of the first IBD medication dose? Use YYYY-MM-DD format in your response. Annotations MUST include day, month, and year (e.g. 01/15/2021). If you have Month or Year level precision, your annotation should take the form of the first possible date consistent with that annotation.",
          "title": "Ibd Medication Start Date"
        }
      },
      "required": [
        "has_mention",
        "spans"
      ],
      "title": "RxStartDateMention",
      "type": "object"
    },
    "RxStatus": {
      "description": "Medication Status (including Intent because chart review is NOT always identical to Med Request)\nhttps://build.fhir.org/valueset-medicationrequest-status.html\nhttps://build.fhir.org/valueset-medicationrequest-intent.html",
      "enum": [
        "Medication order is active (currently prescribed and intended for ongoing use).",
        "Medication is planned/ordered/prescribed but therapy has not yet started.",
        "Medication course is finished (all doses given or intended duration completed).",
        "Medication was stopped or permanently discontinued before completion.",
        "Medication order was canceled/withdrawn before any doses were administered.",
        "Medication is temporarily paused (on-hold, suspended, or interrupted).",
        "None of the above (e.g. specific status not mentioned, status not captured by these options, etc)"
      ],
      "title": "RxStatus",
      "type": "string"
    },
    "RxStatusMention": {
      "properties": {
        "has_mention": {
          "description": "Indicates whether the concept was mentioned in the text (false by default).",
          "title": "Has Mention",
          "type": "boolean"
        },
        "spans": {
          "description": "The verbatim text where this concept was mentioned.",
          "items": {
            "type": "string"
          },
          "title": "Spans",
          "type": "array"
        },
        "rx_status": {
          "$ref": "#/$defs/RxStatus",
          "default": "None of the above (e.g. specific status not mentioned, status not captured by these options, etc)",
          "description": "What, if known, is the status of this medication?"
        }
      },
      "required": [
        "has_mention",
        "spans"
      ],
      "title": "RxStatusMention",
      "type": "object"
    },
    "RxTNFStartDateMention": {
      "properties": {
        "has_mention": {
          "description": "Indicates whether the concept was mentioned in the text (false by default).",
          "title": "Has Mention",
          "type": "boolean"
        },
        "spans": {
          "description": "The verbatim text where this concept was mentioned.",
          "items": {
            "type": "string"
          },
          "title": "Spans",
          "type": "array"
        },
        "anti_tnf_start_date": {
          "anyOf": [
            {
              "type": "string"
            },
            {
              "type": "null"
            }
          ],
          "default": null,
          "description": "What was the date of the first anti-TNF medication dose? Use YYYY-MM-DD format in your response. Annotations MUST include day, month, and year (e.g. 01/15/2021). If you have Month or Year level precision, your annotation should take the form of the first possible date consistent with that annotation.",
          "title": "Anti Tnf Start Date"
        }
      },
      "required": [
        "has_mention",
        "spans"
      ],
      "title": "RxTNFStartDateMention",
      "type": "object"
    },
    "RxTreatmentPhase": {
      "description": "Treatment Phase",
      "enum": [
        "Induction therapy",
        "Maintenance therapy",
        "Rescue therapy",
        "None of the above (e.g. specific phase not mentioned, phase not captured by these options, etc)"
      ],
      "title": "RxTreatmentPhase",
      "type": "string"
    },
    "RxTreatmentPhaseMention": {
      "properties": {
        "has_mention": {
          "description": "Indicates whether the concept was mentioned in the text (false by default).",
          "title": "Has Mention",
          "type": "boolean"
        },
        "spans": {
          "description": "The verbatim text where this concept was mentioned.",
          "items": {
            "type": "string"
          },
          "title": "Spans",
          "type": "array"
        },
        "rx_treatment_phase": {
          "$ref": "#/$defs/RxTreatmentPhase",
          "default": "None of the above (e.g. specific phase not mentioned, phase not captured by these options, etc)",
          "description": "Which, if any, of these IBD treatment phases is the patient in?"
        }
      },
      "required": [
        "has_mention",
        "spans"
      ],
      "title": "RxTreatmentPhaseMention",
      "type": "object"
    }
  },
  "description": "An object-model for annotations of inflammatory bowel disorder observations\nfound in a patient's chart, related to their treatments and associated findings.\nTake care to avoid false positives, like confusing information that only\nappears in family history for patient history. Annotations should indicate\nthe relevant details of the finding, as well as some additional evidence\nmetadata to validate findings post-hoc.",
  "properties": {
    "rx_start_date_mention": {
      "$ref": "#/$defs/RxStartDateMention"
    },
    "rx_tnf_start_date_mention": {
      "$ref": "#/$defs/RxTNFStartDateMention"
    },
    "rx_annotations": {
      "description": "A list of which IBD medications patient is taking currently.",
      "items": {
        "$ref": "#/$defs/RxAnnotation"
      },
      "title": "Rx Annotations",
      "type": "array"
    },
    "anti_tnf_response_mention": {
      "$ref": "#/$defs/AntiTNFResponseMention"
    },
    "rx_effectiveness_mention": {
      "$ref": "#/$defs/RxEffectivenessMention"
    },
    "adverse_drug_event_ibd_mention": {
      "$ref": "#/$defs/AdverseDrugEventIBDMention"
    },
    "adverse_drug_event_anti_tnf_mention": {
      "$ref": "#/$defs/AdverseDrugEventAntiTNFMention"
    }
  },
  "required": [
    "rx_start_date_mention",
    "rx_tnf_start_date_mention",
    "anti_tnf_response_mention",
    "rx_effectiveness_mention",
    "adverse_drug_event_ibd_mention",
    "adverse_drug_event_anti_tnf_mention"
  ],
  "title": "IbdTreatmentAnnotations",
  "type": "object"
}